lecture_pkg/__init__.py
lecture_pkg/cli.py
lecture_pkg/notes.py
gyuminlee_2025_mid_notes-0.0.5.dist-info/METADATA
gyuminlee_2025_mid_notes-0.0.5.dist-info/WHEEL
gyuminlee_2025_mid_notes-0.0.5.dist-info/entry_points.txt
gyuminlee_2025_mid_notes-0.0.5.dist-info/RECORD
