Metadata-Version: 2.4
Name: gyuminlee-2025_mid_notes
Version: 0.0.5
Summary: Lecture Notes
Author-email: gyuminlee <gyuminlee5645@gmail.com>
Classifier: License :: OSI Approved :: MIT License
Classifier: Operating System :: OS Independent
Classifier: Programming Language :: Python :: 3
Requires-Python: >=3.8
